django_fe_version-0.0.1.dist-info/METADATA
django_fe_version-0.0.1.dist-info/RECORD
django_fe_version-0.0.1.dist-info/WHEEL
django_fe_version-0.0.1.dist-info/top_level.txt
fe_version/__init__.py
fe_version/admin.py
fe_version/apps.py
fe_version/models.py
fe_version/tests.py
fe_version/urls.py
fe_version/views.py
fe_version/migrations/__init__.py
