Metadata-Version: 2.1
Name: django-fe-version
Version: 0.0.1
Summary: A simple Django app to show the add version.
Home-page: https://github.com/fernandoe/django-fe-version
Author: Fernando Espíndola
Author-email: fer.esp@gmail.com
License: GPL License
Platform: UNKNOWN
Classifier: Environment :: Web Environment
Classifier: Framework :: Django
Classifier: Framework :: Django :: 2.0
Classifier: Intended Audience :: Developers
Classifier: License :: OSI Approved :: BSD License
Classifier: Operating System :: OS Independent
Classifier: Programming Language :: Python
Classifier: Programming Language :: Python :: 3.5
Classifier: Programming Language :: Python :: 3.6
Classifier: Topic :: Internet :: WWW/HTTP
Classifier: Topic :: Internet :: WWW/HTTP :: Dynamic Content
